README.rst
setup.cfg
setup.py
rsw/__init__.py
rsw/rswlib.py
rsw/version.py
rsw.egg-info/PKG-INFO
rsw.egg-info/SOURCES.txt
rsw.egg-info/dependency_links.txt
rsw.egg-info/entry_points.txt
rsw.egg-info/requires.txt
rsw.egg-info/top_level.txt