Metadata-Version: 1.1
Name: rsw
Version: 2015.12.24
Summary: Command-line tool to facilitate usage of revshareworks.com
Home-page: https://github.com/metaperl/revshareworks
Author: Terrence Brannon
Author-email: revshareworks@gmail.com
License: MIT
Keywords: automated login revenue sharing
Platform: any
Classifier: Development Status :: 3 - Alpha
Classifier: Intended Audience :: End Users/Desktop
Classifier: Topic :: Internet :: WWW/HTTP :: Browsers
Classifier: License :: OSI Approved :: MIT License
Classifier: Programming Language :: Python :: 2
Classifier: Programming Language :: Python :: 2.7
